phcal/CBE_Acids.py
phcal/CBE_calc.py
phcal/PBE_Acids.py
phcal/PBE_calc.py
phcal/__init__.py
phcal-0.1.0.dist-info/LICENSE
phcal-0.1.0.dist-info/METADATA
phcal-0.1.0.dist-info/WHEEL
phcal-0.1.0.dist-info/top_level.txt
phcal-0.1.0.dist-info/RECORD
