Metadata-Version: 2.1
Name: phcal
Version: 0.1.0
Summary: pH calculation based on MBE, CBE and PBE
Author-email: Eric Yuelai Xin <me@eric.xin>
License: LICENSE
Project-URL: Homepage, https://github.com/Eric-xin/pH_Calculation
Project-URL: Issues, https://github.com/Eric-xin/pH_Calculation/issues
Project-URL: Documentation, https://phcal.ericxin.eu/doc/doc.pdf
Keywords: pH,MBE,CBE,PBE,Analytical Chemistry,Chemistry
Classifier: Development Status :: 3 - Alpha
Classifier: Intended Audience :: Science/Research
Classifier: License :: OSI Approved :: MIT License
Classifier: Programming Language :: Python :: 3
Requires-Python: >=3.5
License-File: LICENSE
Requires-Dist: numpy
Requires-Dist: scipy
